[
    {
        "storeId": "2165808180",
        "subwayId": "1",
        "distanceText": "2.0 km",
        "distanceValue": "1965"
    },
    {
        "storeId": "2169503640",
        "subwayId": "2",
        "distanceText": "0.4 km",
        "distanceValue": "362"
    },
    {
        "storeId": "2136336229",
        "subwayId": "5",
        "distanceText": "1.1 km",
        "distanceValue": "1079"
    },
    {
        "storeId": "2156982819",
        "subwayId": "5",
        "distanceText": "1.2 km",
        "distanceValue": "1165"
    },
    {
        "storeId": "2168660886",
        "subwayId": "9",
        "distanceText": "2.0 km",
        "distanceValue": "1982"
    },
    {
        "storeId": "2164826126",
        "subwayId": "11",
        "distanceText": "1.4 km",
        "distanceValue": "1405"
    },
    {
        "storeId": "2132520392",
        "subwayId": "14",
        "distanceText": "1.0 km",
        "distanceValue": "957"
    },
    {
        "storeId": "2162145972",
        "subwayId": "14",
        "distanceText": "1.4 km",
        "distanceValue": "1426"
    },
    {
        "storeId": "2161590113",
        "subwayId": "15",
        "distanceText": "0.6 km",
        "distanceValue": "601"
    },
    {
        "storeId": "2120233063",
        "subwayId": "15",
        "distanceText": "0.8 km",
        "distanceValue": "786"
    },
    {
        "storeId": "2160456277",
        "subwayId": "15",
        "distanceText": "0.8 km",
        "distanceValue": "807"
    },
    {
        "storeId": "2150811182",
        "subwayId": "15",
        "distanceText": "0.9 km",
        "distanceValue": "908"
    },
    {
        "storeId": "2152919871",
        "subwayId": "17",
        "distanceText": "1.2 km",
        "distanceValue": "1217"
    },
    {
        "storeId": "2132527900",
        "subwayId": "17",
        "distanceText": "1.6 km",
        "distanceValue": "1552"
    },
    {
        "storeId": "2152399185",
        "subwayId": "17",
        "distanceText": "1.8 km",
        "distanceValue": "1832"
    },
    {
        "storeId": "2152288196",
        "subwayId": "17",
        "distanceText": "1.9 km",
        "distanceValue": "1866"
    },
    {
        "storeId": "2131078732",
        "subwayId": "18",
        "distanceText": "1.7 km",
        "distanceValue": "1739"
    },
    {
        "storeId": "2131078731",
        "subwayId": "18",
        "distanceText": "1.7 km",
        "distanceValue": "1739"
    },
    {
        "storeId": "2131078733",
        "subwayId": "18",
        "distanceText": "1.7 km",
        "distanceValue": "1739"
    },
    {
        "storeId": "2152919871",
        "subwayId": "19",
        "distanceText": "0.6 km",
        "distanceValue": "562"
    },
    {
        "storeId": "2132527900",
        "subwayId": "19",
        "distanceText": "1.7 km",
        "distanceValue": "1706"
    },
    {
        "storeId": "2164226862",
        "subwayId": "20",
        "distanceText": "0.5 km",
        "distanceValue": "525"
    },
    {
        "storeId": "2164160683",
        "subwayId": "20",
        "distanceText": "0.7 km",
        "distanceValue": "719"
    },
    {
        "storeId": "2154030089",
        "subwayId": "20",
        "distanceText": "0.8 km",
        "distanceValue": "757"
    },
    {
        "storeId": "2164741223",
        "subwayId": "20",
        "distanceText": "0.9 km",
        "distanceValue": "894"
    },
    {
        "storeId": "2154037951",
        "subwayId": "20",
        "distanceText": "0.9 km",
        "distanceValue": "923"
    },
    {
        "storeId": "2152382901",
        "subwayId": "20",
        "distanceText": "1.5 km",
        "distanceValue": "1497"
    },
    {
        "storeId": "2131078733",
        "subwayId": "22",
        "distanceText": "1.9 km",
        "distanceValue": "1930"
    },
    {
        "storeId": "2131078731",
        "subwayId": "22",
        "distanceText": "1.9 km",
        "distanceValue": "1930"
    },
    {
        "storeId": "2131078732",
        "subwayId": "22",
        "distanceText": "1.9 km",
        "distanceValue": "1930"
    },
    {
        "storeId": "2161736102",
        "subwayId": "23",
        "distanceText": "1.3 km",
        "distanceValue": "1294"
    },
    {
        "storeId": "2166053389",
        "subwayId": "23",
        "distanceText": "1.6 km",
        "distanceValue": "1565"
    },
    {
        "storeId": "2131078732",
        "subwayId": "24",
        "distanceText": "0.3 km",
        "distanceValue": "344"
    },
    {
        "storeId": "2131078733",
        "subwayId": "24",
        "distanceText": "0.3 km",
        "distanceValue": "344"
    },
    {
        "storeId": "2131078731",
        "subwayId": "24",
        "distanceText": "0.3 km",
        "distanceValue": "344"
    },
    {
        "storeId": "2134978366",
        "subwayId": "26",
        "distanceText": "1.0 km",
        "distanceValue": "993"
    },
    {
        "storeId": "2156618967",
        "subwayId": "30",
        "distanceText": "1.9 km",
        "distanceValue": "1925"
    },
    {
        "storeId": "2153078562",
        "subwayId": "32",
        "distanceText": "1.2 km",
        "distanceValue": "1235"
    },
    {
        "storeId": "2164668081",
        "subwayId": "32",
        "distanceText": "1.7 km",
        "distanceValue": "1664"
    },
    {
        "storeId": "2160752058",
        "subwayId": "32",
        "distanceText": "1.7 km",
        "distanceValue": "1744"
    },
    {
        "storeId": "2160752058",
        "subwayId": "33",
        "distanceText": "7 m",
        "distanceValue": "7"
    },
    {
        "storeId": "2164668081",
        "subwayId": "33",
        "distanceText": "0.1 km",
        "distanceValue": "130"
    },
    {
        "storeId": "2133161051",
        "subwayId": "33",
        "distanceText": "1.1 km",
        "distanceValue": "1052"
    },
    {
        "storeId": "2164047144",
        "subwayId": "33",
        "distanceText": "1.5 km",
        "distanceValue": "1539"
    },
    {
        "storeId": "2153078562",
        "subwayId": "33",
        "distanceText": "1.8 km",
        "distanceValue": "1819"
    },
    {
        "storeId": "2163129135",
        "subwayId": "34",
        "distanceText": "0.9 km",
        "distanceValue": "889"
    },
    {
        "storeId": "2163512916",
        "subwayId": "34",
        "distanceText": "1.0 km",
        "distanceValue": "1017"
    },
    {
        "storeId": "2153088773",
        "subwayId": "34",
        "distanceText": "1.3 km",
        "distanceValue": "1278"
    },
    {
        "storeId": "2133660057",
        "subwayId": "34",
        "distanceText": "1.3 km",
        "distanceValue": "1316"
    },
    {
        "storeId": "2163346035",
        "subwayId": "34",
        "distanceText": "1.6 km",
        "distanceValue": "1589"
    },
    {
        "storeId": "2162308226",
        "subwayId": "34",
        "distanceText": "1.9 km",
        "distanceValue": "1906"
    },
    {
        "storeId": "2164047144",
        "subwayId": "34",
        "distanceText": "2.0 km",
        "distanceValue": "1974"
    },
    {
        "storeId": "2164268826",
        "subwayId": "37",
        "distanceText": "1.5 km",
        "distanceValue": "1498"
    },
    {
        "storeId": "2166053389",
        "subwayId": "38",
        "distanceText": "1.2 km",
        "distanceValue": "1169"
    },
    {
        "storeId": "2136336229",
        "subwayId": "38",
        "distanceText": "1.2 km",
        "distanceValue": "1215"
    },
    {
        "storeId": "2161736102",
        "subwayId": "38",
        "distanceText": "1.3 km",
        "distanceValue": "1284"
    },
    {
        "storeId": "2156982819",
        "subwayId": "38",
        "distanceText": "1.7 km",
        "distanceValue": "1666"
    },
    {
        "storeId": "2120233063",
        "subwayId": "39",
        "distanceText": "1.0 km",
        "distanceValue": "987"
    },
    {
        "storeId": "2161590113",
        "subwayId": "39",
        "distanceText": "1.2 km",
        "distanceValue": "1193"
    },
    {
        "storeId": "2134757177",
        "subwayId": "39",
        "distanceText": "1.5 km",
        "distanceValue": "1472"
    },
    {
        "storeId": "2150117436",
        "subwayId": "39",
        "distanceText": "1.7 km",
        "distanceValue": "1652"
    },
    {
        "storeId": "2160875383",
        "subwayId": "39",
        "distanceText": "1.7 km",
        "distanceValue": "1702"
    },
    {
        "storeId": "2150811182",
        "subwayId": "39",
        "distanceText": "1.9 km",
        "distanceValue": "1923"
    },
    {
        "storeId": "2160456277",
        "subwayId": "39",
        "distanceText": "2.0 km",
        "distanceValue": "1996"
    },
    {
        "storeId": "2153210007",
        "subwayId": "49",
        "distanceText": "0.7 km",
        "distanceValue": "691"
    },
    {
        "storeId": "2163512916",
        "subwayId": "49",
        "distanceText": "1.1 km",
        "distanceValue": "1136"
    },
    {
        "storeId": "2156982819",
        "subwayId": "49",
        "distanceText": "1.3 km",
        "distanceValue": "1324"
    },
    {
        "storeId": "2153088773",
        "subwayId": "49",
        "distanceText": "1.4 km",
        "distanceValue": "1386"
    },
    {
        "storeId": "2136336229",
        "subwayId": "49",
        "distanceText": "1.6 km",
        "distanceValue": "1645"
    },
    {
        "storeId": "2163346035",
        "subwayId": "49",
        "distanceText": "1.9 km",
        "distanceValue": "1911"
    },
    {
        "storeId": "2158446297",
        "subwayId": "50",
        "distanceText": "1.2 km",
        "distanceValue": "1178"
    },
    {
        "storeId": "2132520392",
        "subwayId": "55",
        "distanceText": "1.5 km",
        "distanceValue": "1508"
    },
    {
        "storeId": "2162145972",
        "subwayId": "55",
        "distanceText": "1.6 km",
        "distanceValue": "1571"
    },
    {
        "storeId": "2158446297",
        "subwayId": "60",
        "distanceText": "1.0 km",
        "distanceValue": "968"
    },
    {
        "storeId": "2166033016",
        "subwayId": "65",
        "distanceText": "0.3 km",
        "distanceValue": "278"
    },
    {
        "storeId": "2134691978",
        "subwayId": "66",
        "distanceText": "0.8 km",
        "distanceValue": "752"
    },
    {
        "storeId": "2155233015",
        "subwayId": "67",
        "distanceText": "1.5 km",
        "distanceValue": "1468"
    },
    {
        "storeId": "2165379893",
        "subwayId": "67",
        "distanceText": "1.6 km",
        "distanceValue": "1641"
    },
    {
        "storeId": "2136336229",
        "subwayId": "68",
        "distanceText": "1.2 km",
        "distanceValue": "1218"
    },
    {
        "storeId": "2165808180",
        "subwayId": "68",
        "distanceText": "1.3 km",
        "distanceValue": "1310"
    },
    {
        "storeId": "2166053389",
        "subwayId": "68",
        "distanceText": "1.6 km",
        "distanceValue": "1551"
    },
    {
        "storeId": "2156982819",
        "subwayId": "68",
        "distanceText": "1.7 km",
        "distanceValue": "1669"
    },
    {
        "storeId": "2161736102",
        "subwayId": "68",
        "distanceText": "1.9 km",
        "distanceValue": "1885"
    },
    {
        "storeId": "2154867152",
        "subwayId": "71",
        "distanceText": "1.5 km",
        "distanceValue": "1479"
    },
    {
        "storeId": "2162308225",
        "subwayId": "72",
        "distanceText": "0.9 km",
        "distanceValue": "872"
    },
    {
        "storeId": "2162308226",
        "subwayId": "72",
        "distanceText": "1.6 km",
        "distanceValue": "1617"
    },
    {
        "storeId": "2161361404",
        "subwayId": "72",
        "distanceText": "1.8 km",
        "distanceValue": "1780"
    },
    {
        "storeId": "2161361403",
        "subwayId": "72",
        "distanceText": "1.8 km",
        "distanceValue": "1780"
    },
    {
        "storeId": "2152399185",
        "subwayId": "72",
        "distanceText": "1.8 km",
        "distanceValue": "1841"
    },
    {
        "storeId": "2152288196",
        "subwayId": "72",
        "distanceText": "1.9 km",
        "distanceValue": "1875"
    },
    {
        "storeId": "2153088773",
        "subwayId": "72",
        "distanceText": "1.9 km",
        "distanceValue": "1905"
    },
    {
        "storeId": "2163346035",
        "subwayId": "72",
        "distanceText": "2.0 km",
        "distanceValue": "1975"
    },
    {
        "storeId": "2154037951",
        "subwayId": "74",
        "distanceText": "1.3 km",
        "distanceValue": "1310"
    },
    {
        "storeId": "2164226862",
        "subwayId": "74",
        "distanceText": "1.5 km",
        "distanceValue": "1527"
    },
    {
        "storeId": "2164693630",
        "subwayId": "74",
        "distanceText": "1.6 km",
        "distanceValue": "1554"
    },
    {
        "storeId": "2154030089",
        "subwayId": "74",
        "distanceText": "1.6 km",
        "distanceValue": "1617"
    },
    {
        "storeId": "2152382901",
        "subwayId": "74",
        "distanceText": "1.7 km",
        "distanceValue": "1727"
    },
    {
        "storeId": "2160857631",
        "subwayId": "74",
        "distanceText": "1.7 km",
        "distanceValue": "1742"
    },
    {
        "storeId": "2164160683",
        "subwayId": "74",
        "distanceText": "1.8 km",
        "distanceValue": "1826"
    },
    {
        "storeId": "2161736102",
        "subwayId": "76",
        "distanceText": "0.1 km",
        "distanceValue": "118"
    },
    {
        "storeId": "2166053389",
        "subwayId": "76",
        "distanceText": "0.4 km",
        "distanceValue": "415"
    },
    {
        "storeId": "2151511067",
        "subwayId": "78",
        "distanceText": "0.9 km",
        "distanceValue": "937"
    },
    {
        "storeId": "2154716359",
        "subwayId": "79",
        "distanceText": "0.1 km",
        "distanceValue": "110"
    },
    {
        "storeId": "2162308227",
        "subwayId": "80",
        "distanceText": "1.6 km",
        "distanceValue": "1565"
    },
    {
        "storeId": "2152895880",
        "subwayId": "80",
        "distanceText": "1.6 km",
        "distanceValue": "1565"
    },
    {
        "storeId": "2152300972",
        "subwayId": "80",
        "distanceText": "1.6 km",
        "distanceValue": "1644"
    },
    {
        "storeId": "2164693630",
        "subwayId": "80",
        "distanceText": "1.9 km",
        "distanceValue": "1892"
    },
    {
        "storeId": "2168660886",
        "subwayId": "82",
        "distanceText": "1.8 km",
        "distanceValue": "1774"
    },
    {
        "storeId": "2162128618",
        "subwayId": "94",
        "distanceText": "1.1 km",
        "distanceValue": "1139"
    },
    {
        "storeId": "2152381955",
        "subwayId": "94",
        "distanceText": "1.1 km",
        "distanceValue": "1141"
    },
    {
        "storeId": "2152382901",
        "subwayId": "94",
        "distanceText": "1.3 km",
        "distanceValue": "1257"
    },
    {
        "storeId": "2132527900",
        "subwayId": "94",
        "distanceText": "1.3 km",
        "distanceValue": "1278"
    },
    {
        "storeId": "2152300972",
        "subwayId": "94",
        "distanceText": "1.8 km",
        "distanceValue": "1788"
    },
    {
        "storeId": "2155233015",
        "subwayId": "95",
        "distanceText": "0.2 km",
        "distanceValue": "221"
    },
    {
        "storeId": "2165379893",
        "subwayId": "95",
        "distanceText": "0.7 km",
        "distanceValue": "666"
    },
    {
        "storeId": "2164693630",
        "subwayId": "98",
        "distanceText": "1.1 km",
        "distanceValue": "1084"
    },
    {
        "storeId": "2160857631",
        "subwayId": "98",
        "distanceText": "1.3 km",
        "distanceValue": "1333"
    },
    {
        "storeId": "2152300972",
        "subwayId": "98",
        "distanceText": "1.7 km",
        "distanceValue": "1699"
    },
    {
        "storeId": "2152382901",
        "subwayId": "98",
        "distanceText": "1.8 km",
        "distanceValue": "1773"
    },
    {
        "storeId": "2154037951",
        "subwayId": "98",
        "distanceText": "1.9 km",
        "distanceValue": "1897"
    },
    {
        "storeId": "2164268826",
        "subwayId": "98",
        "distanceText": "1.9 km",
        "distanceValue": "1944"
    },
    {
        "storeId": "2164668081",
        "subwayId": "99",
        "distanceText": "0.7 km",
        "distanceValue": "738"
    },
    {
        "storeId": "2160752058",
        "subwayId": "99",
        "distanceText": "0.8 km",
        "distanceValue": "784"
    },
    {
        "storeId": "2164226862",
        "subwayId": "99",
        "distanceText": "1.7 km",
        "distanceValue": "1718"
    },
    {
        "storeId": "2164741223",
        "subwayId": "99",
        "distanceText": "1.7 km",
        "distanceValue": "1733"
    },
    {
        "storeId": "2164160683",
        "subwayId": "99",
        "distanceText": "1.8 km",
        "distanceValue": "1779"
    },
    {
        "storeId": "2133161051",
        "subwayId": "99",
        "distanceText": "1.8 km",
        "distanceValue": "1843"
    },
    {
        "storeId": "2154030089",
        "subwayId": "100",
        "distanceText": "0.8 km",
        "distanceValue": "831"
    },
    {
        "storeId": "2152288196",
        "subwayId": "100",
        "distanceText": "1.2 km",
        "distanceValue": "1173"
    },
    {
        "storeId": "2152399185",
        "subwayId": "100",
        "distanceText": "1.2 km",
        "distanceValue": "1207"
    },
    {
        "storeId": "2154037951",
        "subwayId": "100",
        "distanceText": "1.2 km",
        "distanceValue": "1241"
    },
    {
        "storeId": "2152382901",
        "subwayId": "100",
        "distanceText": "1.3 km",
        "distanceValue": "1322"
    },
    {
        "storeId": "2161361403",
        "subwayId": "100",
        "distanceText": "1.4 km",
        "distanceValue": "1436"
    },
    {
        "storeId": "2161361404",
        "subwayId": "100",
        "distanceText": "1.4 km",
        "distanceValue": "1436"
    },
    {
        "storeId": "2164226862",
        "subwayId": "100",
        "distanceText": "1.6 km",
        "distanceValue": "1636"
    },
    {
        "storeId": "2164160683",
        "subwayId": "100",
        "distanceText": "1.7 km",
        "distanceValue": "1701"
    },
    {
        "storeId": "2164741223",
        "subwayId": "100",
        "distanceText": "1.9 km",
        "distanceValue": "1877"
    },
    {
        "storeId": "2164122191",
        "subwayId": "102",
        "distanceText": "1.7 km",
        "distanceValue": "1717"
    },
    {
        "storeId": "2134532153",
        "subwayId": "102",
        "distanceText": "1.8 km",
        "distanceValue": "1756"
    },
    {
        "storeId": "2150272338",
        "subwayId": "104",
        "distanceText": "0.6 km",
        "distanceValue": "560"
    },
    {
        "storeId": "2151355819",
        "subwayId": "104",
        "distanceText": "0.6 km",
        "distanceValue": "573"
    },
    {
        "storeId": "2162145972",
        "subwayId": "107",
        "distanceText": "0.4 km",
        "distanceValue": "365"
    },
    {
        "storeId": "2132520392",
        "subwayId": "107",
        "distanceText": "1.3 km",
        "distanceValue": "1281"
    },
    {
        "storeId": "2158660083",
        "subwayId": "108",
        "distanceText": "0.5 km",
        "distanceValue": "489"
    },
    {
        "storeId": "2151925153",
        "subwayId": "112",
        "distanceText": "1.0 km",
        "distanceValue": "994"
    },
    {
        "storeId": "2168739675",
        "subwayId": "112",
        "distanceText": "1.2 km",
        "distanceValue": "1188"
    },
    {
        "storeId": "2150811182",
        "subwayId": "112",
        "distanceText": "1.5 km",
        "distanceValue": "1470"
    },
    {
        "storeId": "2160456277",
        "subwayId": "112",
        "distanceText": "1.7 km",
        "distanceValue": "1715"
    },
    {
        "storeId": "2150762907",
        "subwayId": "112",
        "distanceText": "1.8 km",
        "distanceValue": "1756"
    },
    {
        "storeId": "2169568531",
        "subwayId": "113",
        "distanceText": "0.2 km",
        "distanceValue": "184"
    },
    {
        "storeId": "2133660057",
        "subwayId": "114",
        "distanceText": "1.1 km",
        "distanceValue": "1101"
    },
    {
        "storeId": "2163129135",
        "subwayId": "114",
        "distanceText": "1.3 km",
        "distanceValue": "1291"
    },
    {
        "storeId": "2164047144",
        "subwayId": "114",
        "distanceText": "1.3 km",
        "distanceValue": "1321"
    },
    {
        "storeId": "2133161051",
        "subwayId": "114",
        "distanceText": "1.7 km",
        "distanceValue": "1693"
    },
    {
        "storeId": "2164122191",
        "subwayId": "116",
        "distanceText": "0.2 km",
        "distanceValue": "189"
    },
    {
        "storeId": "2134532153",
        "subwayId": "116",
        "distanceText": "0.2 km",
        "distanceValue": "228"
    },
    {
        "storeId": "2165808180",
        "subwayId": "120",
        "distanceText": "0.4 km",
        "distanceValue": "450"
    },
    {
        "storeId": "2150762907",
        "subwayId": "121",
        "distanceText": "0.6 km",
        "distanceValue": "556"
    },
    {
        "storeId": "2151925153",
        "subwayId": "121",
        "distanceText": "2.0 km",
        "distanceValue": "1973"
    },
    {
        "storeId": "2166033016",
        "subwayId": "122",
        "distanceText": "1.5 km",
        "distanceValue": "1493"
    },
    {
        "storeId": "2132520392",
        "subwayId": "127",
        "distanceText": "1.0 km",
        "distanceValue": "1005"
    },
    {
        "storeId": "2132527900",
        "subwayId": "127",
        "distanceText": "1.3 km",
        "distanceValue": "1262"
    },
    {
        "storeId": "2162145972",
        "subwayId": "127",
        "distanceText": "1.5 km",
        "distanceValue": "1519"
    },
    {
        "storeId": "2152381955",
        "subwayId": "127",
        "distanceText": "1.8 km",
        "distanceValue": "1784"
    },
    {
        "storeId": "2162128618",
        "subwayId": "127",
        "distanceText": "1.9 km",
        "distanceValue": "1931"
    },
    {
        "storeId": "2164065909",
        "subwayId": "129",
        "distanceText": "1.2 km",
        "distanceValue": "1233"
    },
    {
        "storeId": "2162186193",
        "subwayId": "129",
        "distanceText": "1.7 km",
        "distanceValue": "1682"
    },
    {
        "storeId": "2132521867",
        "subwayId": "132",
        "distanceText": "1.0 km",
        "distanceValue": "977"
    },
    {
        "storeId": "2153078562",
        "subwayId": "133",
        "distanceText": "1.2 km",
        "distanceValue": "1221"
    },
    {
        "storeId": "2160752058",
        "subwayId": "133",
        "distanceText": "1.3 km",
        "distanceValue": "1270"
    },
    {
        "storeId": "2133161051",
        "subwayId": "133",
        "distanceText": "1.4 km",
        "distanceValue": "1381"
    },
    {
        "storeId": "2164668081",
        "subwayId": "133",
        "distanceText": "1.4 km",
        "distanceValue": "1392"
    },
    {
        "storeId": "2133161051",
        "subwayId": "135",
        "distanceText": "1.0 km",
        "distanceValue": "1047"
    },
    {
        "storeId": "2160752058",
        "subwayId": "135",
        "distanceText": "2.0 km",
        "distanceValue": "1952"
    },
    {
        "storeId": "2133660057",
        "subwayId": "135",
        "distanceText": "2.0 km",
        "distanceValue": "1953"
    },
    {
        "storeId": "2134757177",
        "subwayId": "136",
        "distanceText": "1.3 km",
        "distanceValue": "1334"
    },
    {
        "storeId": "2160875383",
        "subwayId": "136",
        "distanceText": "1.6 km",
        "distanceValue": "1576"
    },
    {
        "storeId": "2150117436",
        "subwayId": "136",
        "distanceText": "1.7 km",
        "distanceValue": "1651"
    },
    {
        "storeId": "2133161051",
        "subwayId": "139",
        "distanceText": "0.1 km",
        "distanceValue": "105"
    },
    {
        "storeId": "2160752058",
        "subwayId": "139",
        "distanceText": "1.0 km",
        "distanceValue": "970"
    },
    {
        "storeId": "2164668081",
        "subwayId": "139",
        "distanceText": "1.1 km",
        "distanceValue": "1093"
    },
    {
        "storeId": "2133660057",
        "subwayId": "139",
        "distanceText": "1.2 km",
        "distanceValue": "1163"
    },
    {
        "storeId": "2164047144",
        "subwayId": "139",
        "distanceText": "1.2 km",
        "distanceValue": "1241"
    },
    {
        "storeId": "2163129135",
        "subwayId": "139",
        "distanceText": "1.6 km",
        "distanceValue": "1590"
    },
    {
        "storeId": "2153078562",
        "subwayId": "144",
        "distanceText": "1.8 km",
        "distanceValue": "1756"
    },
    {
        "storeId": "2168660886",
        "subwayId": "145",
        "distanceText": "1.3 km",
        "distanceValue": "1290"
    },
    {
        "storeId": "2160456277",
        "subwayId": "145",
        "distanceText": "2.0 km",
        "distanceValue": "1994"
    },
    {
        "storeId": "2136336229",
        "subwayId": "156",
        "distanceText": "0.2 km",
        "distanceValue": "183"
    },
    {
        "storeId": "2156982819",
        "subwayId": "156",
        "distanceText": "0.6 km",
        "distanceValue": "634"
    },
    {
        "storeId": "2153210007",
        "subwayId": "156",
        "distanceText": "1.8 km",
        "distanceValue": "1782"
    },
    {
        "storeId": "2161736102",
        "subwayId": "158",
        "distanceText": "1.5 km",
        "distanceValue": "1451"
    },
    {
        "storeId": "2166053389",
        "subwayId": "158",
        "distanceText": "1.6 km",
        "distanceValue": "1616"
    },
    {
        "storeId": "2152944019",
        "subwayId": "160",
        "distanceText": "1.6 km",
        "distanceValue": "1574"
    },
    {
        "storeId": "2163512916",
        "subwayId": "164",
        "distanceText": "0.3 km",
        "distanceValue": "305"
    },
    {
        "storeId": "2153088773",
        "subwayId": "164",
        "distanceText": "0.5 km",
        "distanceValue": "526"
    },
    {
        "storeId": "2163346035",
        "subwayId": "164",
        "distanceText": "0.9 km",
        "distanceValue": "853"
    },
    {
        "storeId": "2162308226",
        "subwayId": "164",
        "distanceText": "1.2 km",
        "distanceValue": "1192"
    },
    {
        "storeId": "2163129135",
        "subwayId": "164",
        "distanceText": "1.5 km",
        "distanceValue": "1524"
    },
    {
        "storeId": "2161361403",
        "subwayId": "164",
        "distanceText": "1.9 km",
        "distanceValue": "1865"
    },
    {
        "storeId": "2161361404",
        "subwayId": "164",
        "distanceText": "1.9 km",
        "distanceValue": "1865"
    },
    {
        "storeId": "2153210007",
        "subwayId": "164",
        "distanceText": "1.9 km",
        "distanceValue": "1891"
    },
    {
        "storeId": "2133660057",
        "subwayId": "164",
        "distanceText": "2.0 km",
        "distanceValue": "1951"
    },
    {
        "storeId": "2162308225",
        "subwayId": "164",
        "distanceText": "2.0 km",
        "distanceValue": "1953"
    },
    {
        "storeId": "2160456277",
        "subwayId": "165",
        "distanceText": "0.3 km",
        "distanceValue": "327"
    },
    {
        "storeId": "2150811182",
        "subwayId": "165",
        "distanceText": "0.5 km",
        "distanceValue": "512"
    },
    {
        "storeId": "2161590113",
        "subwayId": "165",
        "distanceText": "1.3 km",
        "distanceValue": "1306"
    },
    {
        "storeId": "2120233063",
        "subwayId": "165",
        "distanceText": "1.7 km",
        "distanceValue": "1706"
    },
    {
        "storeId": "2161590113",
        "subwayId": "166",
        "distanceText": "1.7 km",
        "distanceValue": "1700"
    },
    {
        "storeId": "2134757177",
        "subwayId": "166",
        "distanceText": "1.7 km",
        "distanceValue": "1748"
    },
    {
        "storeId": "2120233063",
        "subwayId": "166",
        "distanceText": "1.9 km",
        "distanceValue": "1885"
    },
    {
        "storeId": "2153088773",
        "subwayId": "173",
        "distanceText": "0.9 km",
        "distanceValue": "852"
    },
    {
        "storeId": "2163512916",
        "subwayId": "173",
        "distanceText": "1.2 km",
        "distanceValue": "1201"
    },
    {
        "storeId": "2163346035",
        "subwayId": "173",
        "distanceText": "1.6 km",
        "distanceValue": "1650"
    },
    {
        "storeId": "2156982819",
        "subwayId": "173",
        "distanceText": "1.7 km",
        "distanceValue": "1681"
    },
    {
        "storeId": "2162308225",
        "subwayId": "173",
        "distanceText": "1.7 km",
        "distanceValue": "1694"
    },
    {
        "storeId": "2136336229",
        "subwayId": "173",
        "distanceText": "1.9 km",
        "distanceValue": "1854"
    },
    {
        "storeId": "2162308226",
        "subwayId": "173",
        "distanceText": "1.9 km",
        "distanceValue": "1916"
    },
    {
        "storeId": "2166053389",
        "subwayId": "174",
        "distanceText": "1.5 km",
        "distanceValue": "1548"
    },
    {
        "storeId": "2161736102",
        "subwayId": "174",
        "distanceText": "1.6 km",
        "distanceValue": "1596"
    },
    {
        "storeId": "2155233015",
        "subwayId": "176",
        "distanceText": "1.4 km",
        "distanceValue": "1446"
    },
    {
        "storeId": "2165379893",
        "subwayId": "176",
        "distanceText": "1.9 km",
        "distanceValue": "1891"
    },
    {
        "storeId": "2120233063",
        "subwayId": "177",
        "distanceText": "0.7 km",
        "distanceValue": "715"
    },
    {
        "storeId": "2161590113",
        "subwayId": "177",
        "distanceText": "1.1 km",
        "distanceValue": "1102"
    },
    {
        "storeId": "2150811182",
        "subwayId": "177",
        "distanceText": "1.8 km",
        "distanceValue": "1817"
    },
    {
        "storeId": "2134757177",
        "subwayId": "177",
        "distanceText": "1.8 km",
        "distanceValue": "1835"
    },
    {
        "storeId": "2160456277",
        "subwayId": "177",
        "distanceText": "1.9 km",
        "distanceValue": "1890"
    },
    {
        "storeId": "2150762907",
        "subwayId": "180",
        "distanceText": "0.7 km",
        "distanceValue": "722"
    },
    {
        "storeId": "2151925153",
        "subwayId": "180",
        "distanceText": "0.9 km",
        "distanceValue": "932"
    },
    {
        "storeId": "2168739675",
        "subwayId": "180",
        "distanceText": "1.0 km",
        "distanceValue": "1036"
    },
    {
        "storeId": "2169568530",
        "subwayId": "181",
        "distanceText": "0.7 km",
        "distanceValue": "684"
    },
    {
        "storeId": "2164268826",
        "subwayId": "183",
        "distanceText": "1.0 km",
        "distanceValue": "991"
    },
    {
        "storeId": "2160857631",
        "subwayId": "183",
        "distanceText": "1.1 km",
        "distanceValue": "1058"
    },
    {
        "storeId": "2164693630",
        "subwayId": "183",
        "distanceText": "1.4 km",
        "distanceValue": "1408"
    },
    {
        "storeId": "2154037951",
        "subwayId": "184",
        "distanceText": "1.0 km",
        "distanceValue": "995"
    },
    {
        "storeId": "2152382901",
        "subwayId": "184",
        "distanceText": "1.2 km",
        "distanceValue": "1211"
    },
    {
        "storeId": "2154030089",
        "subwayId": "184",
        "distanceText": "1.4 km",
        "distanceValue": "1355"
    },
    {
        "storeId": "2164226862",
        "subwayId": "184",
        "distanceText": "1.4 km",
        "distanceValue": "1411"
    },
    {
        "storeId": "2164160683",
        "subwayId": "184",
        "distanceText": "1.6 km",
        "distanceValue": "1615"
    },
    {
        "storeId": "2164741223",
        "subwayId": "184",
        "distanceText": "1.8 km",
        "distanceValue": "1791"
    },
    {
        "storeId": "2164693630",
        "subwayId": "184",
        "distanceText": "2.0 km",
        "distanceValue": "1981"
    },
    {
        "storeId": "2152944019",
        "subwayId": "185",
        "distanceText": "1.7 km",
        "distanceValue": "1743"
    },
    {
        "storeId": "2160456277",
        "subwayId": "186",
        "distanceText": "0.7 km",
        "distanceValue": "749"
    },
    {
        "storeId": "2150811182",
        "subwayId": "186",
        "distanceText": "1.1 km",
        "distanceValue": "1140"
    },
    {
        "storeId": "2161590113",
        "subwayId": "186",
        "distanceText": "1.7 km",
        "distanceValue": "1704"
    },
    {
        "storeId": "2164826126",
        "subwayId": "187",
        "distanceText": "1.1 km",
        "distanceValue": "1139"
    },
    {
        "storeId": "2164268826",
        "subwayId": "188",
        "distanceText": "0.5 km",
        "distanceValue": "457"
    },
    {
        "storeId": "2160857631",
        "subwayId": "188",
        "distanceText": "1.3 km",
        "distanceValue": "1293"
    },
    {
        "storeId": "2164693630",
        "subwayId": "188",
        "distanceText": "1.4 km",
        "distanceValue": "1418"
    },
    {
        "storeId": "2164268826",
        "subwayId": "189",
        "distanceText": "1.2 km",
        "distanceValue": "1250"
    },
    {
        "storeId": "2160857631",
        "subwayId": "189",
        "distanceText": "1.8 km",
        "distanceValue": "1813"
    },
    {
        "storeId": "2158446297",
        "subwayId": "192",
        "distanceText": "1.7 km",
        "distanceValue": "1696"
    },
    {
        "storeId": "2162186193",
        "subwayId": "199",
        "distanceText": "0.4 km",
        "distanceValue": "392"
    },
    {
        "storeId": "2132521867",
        "subwayId": "199",
        "distanceText": "1.2 km",
        "distanceValue": "1237"
    },
    {
        "storeId": "2162308227",
        "subwayId": "199",
        "distanceText": "1.7 km",
        "distanceValue": "1732"
    },
    {
        "storeId": "2152895880",
        "subwayId": "199",
        "distanceText": "1.7 km",
        "distanceValue": "1732"
    },
    {
        "storeId": "2164065909",
        "subwayId": "199",
        "distanceText": "1.8 km",
        "distanceValue": "1828"
    },
    {
        "storeId": "2165808180",
        "subwayId": "202",
        "distanceText": "1.9 km",
        "distanceValue": "1920"
    },
    {
        "storeId": "2167760458",
        "subwayId": "207",
        "distanceText": "1.9 km",
        "distanceValue": "1943"
    },
    {
        "storeId": "2162308227",
        "subwayId": "210",
        "distanceText": "0.4 km",
        "distanceValue": "437"
    },
    {
        "storeId": "2152895880",
        "subwayId": "210",
        "distanceText": "0.4 km",
        "distanceValue": "437"
    },
    {
        "storeId": "2132521867",
        "subwayId": "210",
        "distanceText": "1.9 km",
        "distanceValue": "1917"
    },
    {
        "storeId": "2163129135",
        "subwayId": "212",
        "distanceText": "55 m",
        "distanceValue": "55"
    },
    {
        "storeId": "2133660057",
        "subwayId": "212",
        "distanceText": "0.4 km",
        "distanceValue": "368"
    },
    {
        "storeId": "2164047144",
        "subwayId": "212",
        "distanceText": "1.0 km",
        "distanceValue": "1023"
    },
    {
        "storeId": "2163346035",
        "subwayId": "212",
        "distanceText": "1.2 km",
        "distanceValue": "1243"
    },
    {
        "storeId": "2164741223",
        "subwayId": "212",
        "distanceText": "1.5 km",
        "distanceValue": "1462"
    },
    {
        "storeId": "2162308226",
        "subwayId": "212",
        "distanceText": "1.5 km",
        "distanceValue": "1497"
    },
    {
        "storeId": "2133161051",
        "subwayId": "212",
        "distanceText": "1.6 km",
        "distanceValue": "1619"
    },
    {
        "storeId": "2164160683",
        "subwayId": "212",
        "distanceText": "1.6 km",
        "distanceValue": "1638"
    },
    {
        "storeId": "2153088773",
        "subwayId": "212",
        "distanceText": "1.7 km",
        "distanceValue": "1742"
    },
    {
        "storeId": "2163512916",
        "subwayId": "212",
        "distanceText": "1.9 km",
        "distanceValue": "1888"
    },
    {
        "storeId": "2164226862",
        "subwayId": "212",
        "distanceText": "2.0 km",
        "distanceValue": "1959"
    },
    {
        "storeId": "2133161051",
        "subwayId": "217",
        "distanceText": "2.0 km",
        "distanceValue": "1956"
    },
    {
        "storeId": "2158660083",
        "subwayId": "218",
        "distanceText": "0.9 km",
        "distanceValue": "947"
    },
    {
        "storeId": "2150762907",
        "subwayId": "218",
        "distanceText": "1.5 km",
        "distanceValue": "1466"
    },
    {
        "storeId": "2168739675",
        "subwayId": "219",
        "distanceText": "0.2 km",
        "distanceValue": "209"
    },
    {
        "storeId": "2151925153",
        "subwayId": "219",
        "distanceText": "0.4 km",
        "distanceValue": "360"
    },
    {
        "storeId": "2150762907",
        "subwayId": "219",
        "distanceText": "1.9 km",
        "distanceValue": "1855"
    },
    {
        "storeId": "2156982819",
        "subwayId": "223",
        "distanceText": "0.6 km",
        "distanceValue": "576"
    },
    {
        "storeId": "2136336229",
        "subwayId": "223",
        "distanceText": "1.0 km",
        "distanceValue": "973"
    },
    {
        "storeId": "2153210007",
        "subwayId": "223",
        "distanceText": "1.1 km",
        "distanceValue": "1137"
    },
    {
        "storeId": "2153088773",
        "subwayId": "223",
        "distanceText": "1.7 km",
        "distanceValue": "1667"
    },
    {
        "storeId": "2163512916",
        "subwayId": "223",
        "distanceText": "1.9 km",
        "distanceValue": "1883"
    },
    {
        "storeId": "2165808180",
        "subwayId": "225",
        "distanceText": "1.4 km",
        "distanceValue": "1354"
    },
    {
        "storeId": "2134532153",
        "subwayId": "228",
        "distanceText": "1.4 km",
        "distanceValue": "1442"
    },
    {
        "storeId": "2164122191",
        "subwayId": "228",
        "distanceText": "1.5 km",
        "distanceValue": "1482"
    },
    {
        "storeId": "2150762907",
        "subwayId": "232",
        "distanceText": "1.8 km",
        "distanceValue": "1783"
    },
    {
        "storeId": "2158446297",
        "subwayId": "233",
        "distanceText": "1.1 km",
        "distanceValue": "1109"
    },
    {
        "storeId": "2161361404",
        "subwayId": "236",
        "distanceText": "44 m",
        "distanceValue": "44"
    },
    {
        "storeId": "2161361403",
        "subwayId": "236",
        "distanceText": "44 m",
        "distanceValue": "44"
    },
    {
        "storeId": "2152288196",
        "subwayId": "236",
        "distanceText": "0.4 km",
        "distanceValue": "392"
    },
    {
        "storeId": "2152399185",
        "subwayId": "236",
        "distanceText": "0.5 km",
        "distanceValue": "500"
    },
    {
        "storeId": "2162308226",
        "subwayId": "236",
        "distanceText": "0.6 km",
        "distanceValue": "621"
    },
    {
        "storeId": "2162308225",
        "subwayId": "236",
        "distanceText": "0.8 km",
        "distanceValue": "789"
    },
    {
        "storeId": "2163346035",
        "subwayId": "236",
        "distanceText": "1.0 km",
        "distanceValue": "979"
    },
    {
        "storeId": "2153088773",
        "subwayId": "236",
        "distanceText": "1.5 km",
        "distanceValue": "1529"
    },
    {
        "storeId": "2164741223",
        "subwayId": "236",
        "distanceText": "1.6 km",
        "distanceValue": "1635"
    },
    {
        "storeId": "2164160683",
        "subwayId": "236",
        "distanceText": "1.8 km",
        "distanceValue": "1810"
    },
    {
        "storeId": "2163512916",
        "subwayId": "236",
        "distanceText": "1.9 km",
        "distanceValue": "1910"
    },
    {
        "storeId": "2152300972",
        "subwayId": "238",
        "distanceText": "0.9 km",
        "distanceValue": "872"
    },
    {
        "storeId": "2152381955",
        "subwayId": "238",
        "distanceText": "1.3 km",
        "distanceValue": "1298"
    },
    {
        "storeId": "2162128618",
        "subwayId": "238",
        "distanceText": "1.4 km",
        "distanceValue": "1379"
    },
    {
        "storeId": "2132521867",
        "subwayId": "238",
        "distanceText": "1.9 km",
        "distanceValue": "1861"
    },
    {
        "storeId": "2155233015",
        "subwayId": "242",
        "distanceText": "0.5 km",
        "distanceValue": "474"
    },
    {
        "storeId": "2165379893",
        "subwayId": "242",
        "distanceText": "0.6 km",
        "distanceValue": "647"
    },
    {
        "storeId": "2162145972",
        "subwayId": "244",
        "distanceText": "1.9 km",
        "distanceValue": "1869"
    },
    {
        "storeId": "2155233015",
        "subwayId": "247",
        "distanceText": "1.8 km",
        "distanceValue": "1785"
    },
    {
        "storeId": "2169568531",
        "subwayId": "250",
        "distanceText": "1.1 km",
        "distanceValue": "1131"
    },
    {
        "storeId": "2156618967",
        "subwayId": "250",
        "distanceText": "1.3 km",
        "distanceValue": "1266"
    },
    {
        "storeId": "2133660057",
        "subwayId": "254",
        "distanceText": "0.4 km",
        "distanceValue": "357"
    },
    {
        "storeId": "2164047144",
        "subwayId": "254",
        "distanceText": "0.5 km",
        "distanceValue": "523"
    },
    {
        "storeId": "2163129135",
        "subwayId": "254",
        "distanceText": "0.8 km",
        "distanceValue": "784"
    },
    {
        "storeId": "2133161051",
        "subwayId": "254",
        "distanceText": "0.9 km",
        "distanceValue": "895"
    },
    {
        "storeId": "2160752058",
        "subwayId": "254",
        "distanceText": "1.8 km",
        "distanceValue": "1760"
    },
    {
        "storeId": "2164741223",
        "subwayId": "254",
        "distanceText": "1.8 km",
        "distanceValue": "1809"
    },
    {
        "storeId": "2164668081",
        "subwayId": "254",
        "distanceText": "1.9 km",
        "distanceValue": "1883"
    },
    {
        "storeId": "2164160683",
        "subwayId": "254",
        "distanceText": "2.0 km",
        "distanceValue": "1960"
    },
    {
        "storeId": "2163346035",
        "subwayId": "254",
        "distanceText": "2.0 km",
        "distanceValue": "1972"
    },
    {
        "storeId": "2153088773",
        "subwayId": "255",
        "distanceText": "0.7 km",
        "distanceValue": "736"
    },
    {
        "storeId": "2162308225",
        "subwayId": "255",
        "distanceText": "0.9 km",
        "distanceValue": "930"
    },
    {
        "storeId": "2163346035",
        "subwayId": "255",
        "distanceText": "1.1 km",
        "distanceValue": "1073"
    },
    {
        "storeId": "2162308226",
        "subwayId": "255",
        "distanceText": "1.2 km",
        "distanceValue": "1217"
    },
    {
        "storeId": "2163512916",
        "subwayId": "255",
        "distanceText": "1.2 km",
        "distanceValue": "1221"
    },
    {
        "storeId": "2161361404",
        "subwayId": "255",
        "distanceText": "1.7 km",
        "distanceValue": "1689"
    },
    {
        "storeId": "2161361403",
        "subwayId": "255",
        "distanceText": "1.7 km",
        "distanceValue": "1689"
    },
    {
        "storeId": "2152399185",
        "subwayId": "255",
        "distanceText": "2.0 km",
        "distanceValue": "1968"
    },
    {
        "storeId": "2134978366",
        "subwayId": "256",
        "distanceText": "1.6 km",
        "distanceValue": "1642"
    },
    {
        "storeId": "2164693630",
        "subwayId": "257",
        "distanceText": "0.4 km",
        "distanceValue": "388"
    },
    {
        "storeId": "2160857631",
        "subwayId": "257",
        "distanceText": "0.6 km",
        "distanceValue": "641"
    },
    {
        "storeId": "2164268826",
        "subwayId": "257",
        "distanceText": "1.3 km",
        "distanceValue": "1252"
    },
    {
        "storeId": "2131078733",
        "subwayId": "261",
        "distanceText": "1.1 km",
        "distanceValue": "1059"
    },
    {
        "storeId": "2131078731",
        "subwayId": "261",
        "distanceText": "1.1 km",
        "distanceValue": "1059"
    },
    {
        "storeId": "2131078732",
        "subwayId": "261",
        "distanceText": "1.1 km",
        "distanceValue": "1059"
    },
    {
        "storeId": "2152895880",
        "subwayId": "262",
        "distanceText": "0.5 km",
        "distanceValue": "512"
    },
    {
        "storeId": "2162308227",
        "subwayId": "262",
        "distanceText": "0.5 km",
        "distanceValue": "512"
    },
    {
        "storeId": "2132521867",
        "subwayId": "262",
        "distanceText": "1.1 km",
        "distanceValue": "1099"
    },
    {
        "storeId": "2162186193",
        "subwayId": "262",
        "distanceText": "1.2 km",
        "distanceValue": "1248"
    },
    {
        "storeId": "2164693630",
        "subwayId": "264",
        "distanceText": "1.7 km",
        "distanceValue": "1669"
    },
    {
        "storeId": "2160857631",
        "subwayId": "264",
        "distanceText": "1.8 km",
        "distanceValue": "1780"
    },
    {
        "storeId": "2165808180",
        "subwayId": "265",
        "distanceText": "1.1 km",
        "distanceValue": "1110"
    },
    {
        "storeId": "2166053389",
        "subwayId": "265",
        "distanceText": "1.5 km",
        "distanceValue": "1512"
    },
    {
        "storeId": "2161736102",
        "subwayId": "265",
        "distanceText": "1.9 km",
        "distanceValue": "1879"
    },
    {
        "storeId": "2160456277",
        "subwayId": "268",
        "distanceText": "1.3 km",
        "distanceValue": "1330"
    },
    {
        "storeId": "2161590113",
        "subwayId": "268",
        "distanceText": "1.4 km",
        "distanceValue": "1373"
    },
    {
        "storeId": "2150811182",
        "subwayId": "268",
        "distanceText": "1.5 km",
        "distanceValue": "1516"
    },
    {
        "storeId": "2120233063",
        "subwayId": "268",
        "distanceText": "1.6 km",
        "distanceValue": "1558"
    },
    {
        "storeId": "2131078733",
        "subwayId": "271",
        "distanceText": "1.2 km",
        "distanceValue": "1202"
    },
    {
        "storeId": "2131078731",
        "subwayId": "271",
        "distanceText": "1.2 km",
        "distanceValue": "1202"
    },
    {
        "storeId": "2131078732",
        "subwayId": "271",
        "distanceText": "1.2 km",
        "distanceValue": "1202"
    },
    {
        "storeId": "2163129135",
        "subwayId": "273",
        "distanceText": "1.5 km",
        "distanceValue": "1538"
    },
    {
        "storeId": "2153210007",
        "subwayId": "273",
        "distanceText": "1.7 km",
        "distanceValue": "1712"
    },
    {
        "storeId": "2163512916",
        "subwayId": "273",
        "distanceText": "1.8 km",
        "distanceValue": "1772"
    },
    {
        "storeId": "2133660057",
        "subwayId": "273",
        "distanceText": "2.0 km",
        "distanceValue": "1957"
    },
    {
        "storeId": "2151355819",
        "subwayId": "275",
        "distanceText": "1.5 km",
        "distanceValue": "1541"
    },
    {
        "storeId": "2150272338",
        "subwayId": "275",
        "distanceText": "1.9 km",
        "distanceValue": "1945"
    },
    {
        "storeId": "2169503640",
        "subwayId": "276",
        "distanceText": "1.5 km",
        "distanceValue": "1483"
    },
    {
        "storeId": "2164693630",
        "subwayId": "277",
        "distanceText": "1.4 km",
        "distanceValue": "1402"
    },
    {
        "storeId": "2160857631",
        "subwayId": "277",
        "distanceText": "1.6 km",
        "distanceValue": "1582"
    },
    {
        "storeId": "2164668081",
        "subwayId": "277",
        "distanceText": "1.8 km",
        "distanceValue": "1808"
    },
    {
        "storeId": "2164268826",
        "subwayId": "277",
        "distanceText": "1.8 km",
        "distanceValue": "1840"
    },
    {
        "storeId": "2160752058",
        "subwayId": "277",
        "distanceText": "1.9 km",
        "distanceValue": "1853"
    },
    {
        "storeId": "2154037951",
        "subwayId": "277",
        "distanceText": "1.9 km",
        "distanceValue": "1865"
    },
    {
        "storeId": "2164226862",
        "subwayId": "277",
        "distanceText": "2.0 km",
        "distanceValue": "1996"
    },
    {
        "storeId": "2152919871",
        "subwayId": "279",
        "distanceText": "1.8 km",
        "distanceValue": "1795"
    },
    {
        "storeId": "2169568531",
        "subwayId": "279",
        "distanceText": "1.8 km",
        "distanceValue": "1795"
    },
    {
        "storeId": "2132520392",
        "subwayId": "279",
        "distanceText": "1.8 km",
        "distanceValue": "1823"
    },
    {
        "storeId": "2169568531",
        "subwayId": "280",
        "distanceText": "1.3 km",
        "distanceValue": "1339"
    },
    {
        "storeId": "2154867152",
        "subwayId": "281",
        "distanceText": "1.6 km",
        "distanceValue": "1637"
    },
    {
        "storeId": "2152381955",
        "subwayId": "282",
        "distanceText": "0.5 km",
        "distanceValue": "497"
    },
    {
        "storeId": "2162128618",
        "subwayId": "282",
        "distanceText": "0.8 km",
        "distanceValue": "820"
    },
    {
        "storeId": "2152300972",
        "subwayId": "282",
        "distanceText": "1.6 km",
        "distanceValue": "1557"
    },
    {
        "storeId": "2162145972",
        "subwayId": "282",
        "distanceText": "1.8 km",
        "distanceValue": "1773"
    },
    {
        "storeId": "2152944019",
        "subwayId": "283",
        "distanceText": "1.6 km",
        "distanceValue": "1623"
    },
    {
        "storeId": "2152919871",
        "subwayId": "283",
        "distanceText": "1.7 km",
        "distanceValue": "1669"
    },
    {
        "storeId": "2136336229",
        "subwayId": "284",
        "distanceText": "1.9 km",
        "distanceValue": "1915"
    },
    {
        "storeId": "2167760458",
        "subwayId": "288",
        "distanceText": "1.0 km",
        "distanceValue": "1041"
    }
]